odoo/addons/connector_equipment/README.rst
odoo/addons/connector_equipment/__init__.py
odoo/addons/connector_equipment/__manifest__.py
odoo/addons/connector_equipment/demo/backend_equipment_demo.xml
odoo/addons/connector_equipment/i18n/connector_equipment.pot
odoo/addons/connector_equipment/models/__init__.py
odoo/addons/connector_equipment/models/backend_equipment.py
odoo/addons/connector_equipment/models/maintenance_equipment.py
odoo/addons/connector_equipment/readme/CONFIGURE.rst
odoo/addons/connector_equipment/readme/CONTRIBUTORS.rst
odoo/addons/connector_equipment/readme/DESCRIPTION.rst
odoo/addons/connector_equipment/readme/USAGE.rst
odoo/addons/connector_equipment/security/ir.model.access.csv
odoo/addons/connector_equipment/static/description/icon.png
odoo/addons/connector_equipment/static/description/index.html
odoo/addons/connector_equipment/tests/__init__.py
odoo/addons/connector_equipment/tests/test_connector_equipment.py
odoo/addons/connector_equipment/views/backend_equipment.xml
odoo/addons/connector_equipment/views/maintenance_equipment.xml
odoo12_addon_connector_equipment-12.0.1.0.0.99.dev15.dist-info/METADATA
odoo12_addon_connector_equipment-12.0.1.0.0.99.dev15.dist-info/WHEEL
odoo12_addon_connector_equipment-12.0.1.0.0.99.dev15.dist-info/top_level.txt
odoo12_addon_connector_equipment-12.0.1.0.0.99.dev15.dist-info/RECORD
